sgeom/__init__.py
sgeom/sgeom.py
sgeom-0.1.dist-info/AUTHORS.md
sgeom-0.1.dist-info/LICENSE
sgeom-0.1.dist-info/METADATA
sgeom-0.1.dist-info/WHEEL
sgeom-0.1.dist-info/top_level.txt
sgeom-0.1.dist-info/RECORD
